{"target": "http://pubannotation.org/docs/sourcedb/BB-norm@ldeleger/sourceid/BB-norm-F-27020288-001", "sourcedb": "BB-norm@ldeleger", "sourceid": "BB-norm-F-27020288-001", "text": "Several models of EPS assembly have been proposed for L. lactis (Kleerebezem et al. 1999; Laws et al. 2001), Streptococcus pneumoniae (Bentley et al. 2006), and Lactobacillus rhamnosus (Lebeer et al. 2009).\n However, in addition to the \u201cflippase-like\u201d route, it could be \npossible, in LAB, another route involving ABC transporters, although the\n export-polymerization pathway for EPS production in LAB has not yet \nbeen demonstrated.\n", "project": "bionlp-ost-19-BB-norm-train", "denotations": [{"id": "T1", "span": {"begin": 54, "end": 63}, "obj": "Microorganism"}, {"id": "T2", "span": {"begin": 109, "end": 133}, "obj": "Microorganism"}, {"id": "T3", "span": {"begin": 161, "end": 184}, "obj": "Microorganism"}, {"id": "T4", "span": {"begin": 285, "end": 288}, "obj": "Phenotype"}, {"id": "T5", "span": {"begin": 380, "end": 394}, "obj": "Phenotype"}, {"id": "T6", "span": {"begin": 398, "end": 401}, "obj": "Phenotype"}], "attributes": [{"id": "A4", "pred": "OntoBiotope", "subj": "T4", "obj": "OBT:000019"}, {"id": "A5", "pred": "OntoBiotope", "subj": "T5", "obj": "OBT:000019"}, {"id": "A6", "pred": "OntoBiotope", "subj": "T6", "obj": "OBT:000019"}, {"id": "A2", "pred": "NCBI_Taxonomy", "subj": "T2", "obj": "1313"}, {"id": "A3", "pred": "NCBI_Taxonomy", "subj": "T3", "obj": "47715"}, {"id": "A1", "pred": "NCBI_Taxonomy", "subj": "T1", "obj": "1358"}]}